doc_utils/__init__.py
doc_utils/chunk_doc_utils.py
doc_utils/doc_utils.py
doc_utils/errors.py
doc_utils/read_operator.py
doc_utils/read_utils.py
doc_utils/write_utils.py
tests/__init__.py
tests/conftest.py
tests/test_class_based.py
tests/test_read_utils.py
document_utils-1.8.1.dist-info/LICENSE
document_utils-1.8.1.dist-info/METADATA
document_utils-1.8.1.dist-info/WHEEL
document_utils-1.8.1.dist-info/top_level.txt
document_utils-1.8.1.dist-info/RECORD
