Metadata-Version: 2.1
Name: document-utils
Version: 1.8.1
Summary: Document utilities for Python packages.
Home-page: UNKNOWN
Author: Relevance AI
Author-email: dev@vctr.ai
License: UNKNOWN
Platform: UNKNOWN
Requires-Dist: pandas
